convsn/__init__.py
convsn/distance.py
convsn/temperature.py
convsn-0.0.4.dist-info/METADATA
convsn-0.0.4.dist-info/WHEEL
convsn-0.0.4.dist-info/top_level.txt
convsn-0.0.4.dist-info/RECORD
