Metadata-Version: 2.1
Name: convsn
Version: 0.0.4
Summary: A conversion package
Author: oluyemi
Author-email: yemiwebby@gmail.com
License: MIT
Keywords: conversion
Classifier: Development Status :: 3 - Alpha
Classifier: Intended Audience :: Developers
Classifier: License :: OSI Approved :: MIT License
Classifier: Programming Language :: Python :: 3
